dbcat/__init__.py
dbcat/__main__.py
dbcat/alembic.ini
dbcat/amundsen.py
dbcat/api.py
dbcat/catalog/__init__.py
dbcat/catalog/catalog.py
dbcat/catalog/db.py
dbcat/catalog/models.py
dbcat/catalog/pii_types.py
dbcat/catalog/sqlite_extractor.py
dbcat/cli.py
dbcat/datahub.py
dbcat/generators.py
dbcat/migrations/__init__.py
dbcat/migrations/env.py
dbcat/migrations/script.py.mako
dbcat/migrations/versions/0fed90ee2030_added_service_name_for_oracle.py
dbcat/migrations/versions/3509a9f07432_add_athena_columns.py
dbcat/migrations/versions/377a3427ceb4_add_plugin_column.py
dbcat/migrations/versions/477d6d4b6ad7_add_update_create_columns.py
dbcat/migrations/versions/7d2638f2ab5f_add_tasks_table.py
dbcat/migrations/versions/__init__.py
dbcat/migrations/versions/d1daff1715f7_initial_run.py
dbcat/migrations/versions/d2c711b84996_add_pii_type_enum_to_column.py
dbcat/settings.py
dbcat-0.15.0.dist-info/entry_points.txt
dbcat-0.15.0.dist-info/LICENSE
dbcat-0.15.0.dist-info/WHEEL
dbcat-0.15.0.dist-info/METADATA
dbcat-0.15.0.dist-info/RECORD
