Metadata-Version: 2.1
Name: dbcat
Version: 0.15.0
Summary: Tokern Data Catalog
Home-page: https://tokern.io/
License: MIT
Keywords: data-catalog,postgres,snowflake,redshift,glue,bigquery
Author: Tokern
Author-email: info@tokern.io
Requires-Python: >=3.8,<=3.10.8
Classifier: Development Status :: 3 - Alpha
Classifier: Intended Audience :: Developers
Classifier: License :: OSI Approved :: MIT License
Classifier: Programming Language :: Python
Classifier: Programming Language :: Python :: 3
Classifier: Programming Language :: Python :: 3.8
Classifier: Programming Language :: Python :: 3.9
Classifier: Programming Language :: Python :: 3.10
Classifier: Programming Language :: Python :: 3
Classifier: Programming Language :: Python :: 3.10
Classifier: Programming Language :: Python :: 3.8
Classifier: Programming Language :: Python :: 3.9
Classifier: Topic :: Database
Classifier: Topic :: Software Development
Classifier: Topic :: Software Development :: Libraries :: Python Modules
Provides-Extra: datahub
Requires-Dist: PyMySQL (>=1.0.2,<2.0.0)
Requires-Dist: PyYAML
Requires-Dist: SQLAlchemy (>=1.3.24,<1.4.0)
Requires-Dist: acryl-datahub (>=0.8.16,<0.9.0); extra == "datahub"
Requires-Dist: alembic (>=1.6.5,<2.0.0)
Requires-Dist: amundsen-databuilder[athena,bigquery,glue,rds,snowflake] (>=7,<8)
Requires-Dist: boto3 (==1.17.23)
Requires-Dist: botocore (>=1.20.23,<1.21.0)
Requires-Dist: click
Requires-Dist: dataclasses (>=0.6); python_version >= "3.6" and python_version < "3.7"
Requires-Dist: great-expectations (>=0.13.42,<0.14.0); extra == "datahub"
Requires-Dist: greenlet (>=2.0.1,<3.0.0)
Requires-Dist: psycopg2 (>=2.9.5,<3.0.0)
Requires-Dist: pyathena[sqlalchemy] (==1.11.5)
Requires-Dist: pydantic (>=1.8.2,<2.0.0)
Requires-Dist: pyhocon (>=0.3.58,<0.4.0)
Requires-Dist: pyparsing (>=2.0,<3.0)
Requires-Dist: snowflake-sqlalchemy (==1.2.4)
Requires-Dist: sqlalchemy-mixins (>=1.5,<2.0)
Requires-Dist: sqlalchemy-utils (>=0.38.3,<0.39.0)
Requires-Dist: typer (>=0.4.0,<0.5.0)
Project-URL: Repository, https://github.com/tokern/dbcat/
